nimoy/__init__.py
nimoy/main.py
nimoy/spec_runner.py
nimoy/specification.py
nimoy/assertions/__init__.py
nimoy/assertions/exceptions.py
nimoy/assertions/mocks.py
nimoy/assertions/power.py
nimoy/ast_tools/__init__.py
nimoy/ast_tools/ast_chain.py
nimoy/ast_tools/ast_metadata.py
nimoy/ast_tools/expression_transformer.py
nimoy/ast_tools/feature_blocks.py
nimoy/ast_tools/features.py
nimoy/ast_tools/specs.py
nimoy/compare/__init__.py
nimoy/compare/internal.py
nimoy/compare/types.py
nimoy/context/__init__.py
nimoy/context/feature_block_context.py
nimoy/runner/__init__.py
nimoy/runner/exceptions.py
nimoy/runner/fs_resource_reader.py
nimoy/runner/metadata.py
nimoy/runner/spec_executor.py
nimoy/runner/spec_finder.py
nimoy/runner/spec_loader.py
nimoy/runner/spec_reader.py
nimoy/runner/unittest_execution_framework.py
nimoy_framework-1.1.1.dist-info/LICENSE
nimoy_framework-1.1.1.dist-info/METADATA
nimoy_framework-1.1.1.dist-info/WHEEL
nimoy_framework-1.1.1.dist-info/entry_points.txt
nimoy_framework-1.1.1.dist-info/top_level.txt
nimoy_framework-1.1.1.dist-info/RECORD
