Metadata-Version: 2.1
Name: nimoy-framework
Version: 1.1.1
Summary: A testing and specification framework for Python 3, heavily inspired by the Spock Framework
Home-page: https://github.com/browncoat-ninjas/nimoy
Author: Noam Tenne, Yoav Luft
Author-email: noam@10ne.org
License: Apache License
Keywords: test unittest specification
Platform: unix
Platform: linux
Platform: osx
Classifier: Development Status :: 5 - Production/Stable
Classifier: Intended Audience :: Developers
Classifier: License :: OSI Approved :: Apache Software License
Classifier: Operating System :: POSIX
Classifier: Operating System :: MacOS :: MacOS X
Classifier: Topic :: Software Development :: Testing
Classifier: Topic :: Software Development :: Libraries
Classifier: Topic :: Utilities
Classifier: Programming Language :: Python :: 3
Classifier: Programming Language :: Python :: 3.9
License-File: LICENSE
Requires-Dist: pyhamcrest (==2.0.2)
Requires-Dist: urllib3 (==1.26.5)
Requires-Dist: astor (==0.8.1)
